{
    "format_version": "1.12.0",
    "minecraft:recipe_shaped": {
        "description": {
            "identifier": "minecraft:polished_blackstone_brick_double_slab"
        },
        "tags": [ "crafting_table" ],
        "pattern": [
            "A",
            "A"
        ],
        "key": {
            "A": "minecraft:polished_blackstone_brick_slab"
        },
        "result": {
            "item": "minecraft:polished_blackstone_brick_double_slab",
            "count": 1
        }
    }
}